plugwise_usb/__init__.py
plugwise_usb/api.py
plugwise_usb/constants.py
plugwise_usb/exceptions.py
plugwise_usb/py.typed
plugwise_usb/connection/__init__.py
plugwise_usb/connection/manager.py
plugwise_usb/connection/py.typed
plugwise_usb/connection/queue.py
plugwise_usb/connection/receiver.py
plugwise_usb/connection/sender.py
plugwise_usb/helpers/__init__.py
plugwise_usb/helpers/cache.py
plugwise_usb/helpers/util.py
plugwise_usb/messages/__init__.py
plugwise_usb/messages/properties.py
plugwise_usb/messages/py.typed
plugwise_usb/messages/requests.py
plugwise_usb/messages/responses.py
plugwise_usb/network/__init__.py
plugwise_usb/network/cache.py
plugwise_usb/network/py.typed
plugwise_usb/network/registry.py
plugwise_usb/nodes/__init__.py
plugwise_usb/nodes/celsius.py
plugwise_usb/nodes/circle.py
plugwise_usb/nodes/circle_plus.py
plugwise_usb/nodes/node.py
plugwise_usb/nodes/py.typed
plugwise_usb/nodes/scan.py
plugwise_usb/nodes/sed.py
plugwise_usb/nodes/sense.py
plugwise_usb/nodes/stealth.py
plugwise_usb/nodes/switch.py
plugwise_usb/nodes/helpers/__init__.py
plugwise_usb/nodes/helpers/cache.py
plugwise_usb/nodes/helpers/counter.py
plugwise_usb/nodes/helpers/firmware.py
plugwise_usb/nodes/helpers/pulses.py
plugwise_usb/nodes/helpers/py.typed
plugwise_usb/nodes/helpers/subscription.py
plugwise_usb-0.47.2.dist-info/licenses/LICENSE
plugwise_usb-0.47.2.dist-info/METADATA
plugwise_usb-0.47.2.dist-info/WHEEL
plugwise_usb-0.47.2.dist-info/top_level.txt
plugwise_usb-0.47.2.dist-info/RECORD
