Metadata-Version: 2.4
Name: plugwise_usb
Version: 0.47.2
Author: Plugwise device owners
Maintainer: arnoutd_77, bouwew, brefra, CoMPaTech, dirixmjm
License-Expression: MIT
Project-URL: Source Code, https://github.com/plugwise/python-plugwise-usb
Project-URL: Bug Reports, https://github.com/plugwise/python-plugwise-usb/issues
Keywords: home,automation,plugwise,module,usb
Classifier: Development Status :: 5 - Production/Stable
Classifier: Intended Audience :: Developers
Classifier: Operating System :: OS Independent
Classifier: Programming Language :: Python :: 3.14
Classifier: Programming Language :: Python :: 3.13
Classifier: Topic :: Home Automation
Requires-Python: >=3.13.0
License-File: LICENSE
Requires-Dist: pyserial-asyncio-fast
Requires-Dist: aiofiles
Requires-Dist: crcmod
Requires-Dist: semver
Dynamic: license-file
